tighnari/__init__.py
tighnari-0.1.6.dist-info/LICENSE
tighnari-0.1.6.dist-info/METADATA
tighnari-0.1.6.dist-info/WHEEL
tighnari-0.1.6.dist-info/RECORD
